LICENSE
MANIFEST.in
README.rst
radioglobo.py
setup.py
radioglobo.egg-info/PKG-INFO
radioglobo.egg-info/SOURCES.txt
radioglobo.egg-info/dependency_links.txt
radioglobo.egg-info/entry_points.txt
radioglobo.egg-info/requires.txt
radioglobo.egg-info/top_level.txt