Metadata-Version: 1.1
Name: radioglobo
Version: 0.1
Summary: Script to play radioglobo.com radio streaming in the shell
Home-page: https://github.com/rafaelmartins/radioglobo
Author: Rafael Goncalves Martins
Author-email: rafael@rafaelmartins.eng.br
License: BSD
Platform: UNKNOWN
Classifier: Development Status :: 3 - Alpha
Classifier: Environment :: Console
Classifier: License :: OSI Approved :: BSD License
Classifier: Operating System :: OS Independent
Classifier: Programming Language :: Python :: 2.7
Classifier: Topic :: Multimedia :: Sound/Audio
